cmgp/__init__.py
cmgp/cmgp.py
cmgp/logger.py
cmgp/version.py
cmgp/datasets/__init__.py
cmgp/datasets/dataset_ihdp.py
cmgp/datasets/dataset_twins.py
cmgp/datasets/network.py
cmgp/utils/__init__.py
cmgp/utils/metrics.py
cmgp/utils/random.py
cmgp-0.1.2.dist-info/METADATA
cmgp-0.1.2.dist-info/WHEEL
cmgp-0.1.2.dist-info/top_level.txt
cmgp-0.1.2.dist-info/RECORD
