Metadata-Version: 2.1
Name: cmgp
Version: 0.1.2
Summary: Bayesian Inference of Individualized Treatment Effects using Multi-task Gaussian Processes
Home-page: https://github.com/vanderschaarlab/mlforhealthlabpub/tree/main/alg/causal_multitask_gaussian_processes_ite
Author: Ahmed M. Alaa
Author-email: 
License: BSD-3-Clause
Platform: UNKNOWN
Classifier: Programming Language :: Python :: 3
Classifier: Topic :: Scientific/Engineering :: Artificial Intelligence
Classifier: Intended Audience :: Healthcare Industry
Classifier: License :: OSI Approved :: BSD License
Classifier: Operating System :: OS Independent
Requires-Dist: googledrivedownloader
Requires-Dist: GPy
Requires-Dist: loguru
Requires-Dist: matplotlib
Requires-Dist: numpy
Requires-Dist: pandas
Requires-Dist: requests
Requires-Dist: scikit-learn
Requires-Dist: scipy
